qualisicherung/__init__.py
qualisicherung/main.py
qualisicherung/skeleton.py
qualisicherung-0.0.6.dist-info/AUTHORS.rst
qualisicherung-0.0.6.dist-info/LICENSE.txt
qualisicherung-0.0.6.dist-info/METADATA
qualisicherung-0.0.6.dist-info/WHEEL
qualisicherung-0.0.6.dist-info/top_level.txt
qualisicherung-0.0.6.dist-info/RECORD
