Metadata-Version: 2.1
Name: qualisicherung
Version: 0.0.6
Summary: Add a short description here!
Home-page: https://github.com/pyscaffold/pyscaffold/
Author: Henning HÃ¤cker
Author-email: henning.haecker+github.com@gmail.com
License: mit
Project-URL: Documentation, https://pyscaffold.org/
Platform: any
Classifier: Development Status :: 4 - Beta
Classifier: Programming Language :: Python
Provides-Extra: testing
Requires-Dist: pytest ; extra == 'testing'
Requires-Dist: pytest-cov ; extra == 'testing'
